dyadic_tiling/__init__.py
dyadic_tiling/dyadic_cube.py
dyadic_tiling/dyadic_cube_set.py
dyadic_tiling/morton_encoding.py
dyadic_tiling/point.py
dyadic_tiling/point_set.py
dyadic_tiling/sets.py
dyadic_tiling/stopping_time.py
dyadic_tiling-0.2.0.dist-info/licenses/LICENSE
dyadic_tiling-0.2.0.dist-info/METADATA
dyadic_tiling-0.2.0.dist-info/WHEEL
dyadic_tiling-0.2.0.dist-info/top_level.txt
dyadic_tiling-0.2.0.dist-info/RECORD
