Metadata-Version: 2.4
Name: dyadic-tiling
Version: 0.2.0
Summary: Morton encoded dyadic cubes and points for efficient space decomposition.
Author-email: Benjamin Walker <mail@benwalker.co.uk>
License-Expression: MIT
Project-URL: Homepage, https://github.com/Benjamin-Walker/dyadic-tiling
Project-URL: Bug Tracker, https://github.com/Benjamin-Walker/dyadic-tiling/issues
Keywords: dyadic cube,Morton code,spatial indexing,stopping time
Classifier: Development Status :: 4 - Beta
Classifier: Intended Audience :: Science/Research
Classifier: Programming Language :: Python :: 3
Classifier: Programming Language :: Python :: 3.8
Classifier: Topic :: Scientific/Engineering :: Mathematics
Classifier: Topic :: Software Development :: Libraries :: Python Modules
Requires-Python: >=3.8
License-File: LICENSE
Requires-Dist: sortedcontainers>=2.4
Dynamic: license-file
